<?xml version="1.0" encoding="UTF-8"?>
<interface>
  <requires lib="gtk" version="4.0"/>
  <requires lib="adw" version="1.0" />
  <template class="ImageDropPage" parent="AdwBin">
    <property name="hexpand">true</property>
    <property name="vexpand">true</property>
    <property name="halign">fill</property>
    <property name="valign">fill</property>
    <property name="child">
      <object class="GtkOverlay" id="overlay">
        <child type="overlay">
          <object class="AdwStatusPage" id="status">
            <property name="title" translatable="yes">Drop Image</property>
            <property name="icon-name">image-missing-symbolic</property>
          </object>
        </child>
        <property name="child">
          <object class="ImageThiefPanel" id="thief_panel"></object>
        </property>
      </object>
    </property>
  </template>
</interface>